{
    "sebi_code": "FSIF/O/E/ELSF/25/10/0001/FTMF",
    "fund_name": "Sapphire Equity Long- Short SIF",
    "fund_type": "An open-ended equity investment strategy investing in listed equity and equity related instruments including limited short exposure in equity through derivative instruments",
    "category": "Equity Long-Short Fund",
    "riskometer_at_launch": "Risk Level 5",
    "riskometer_as_on_date": "Risk Level 5",
    "potential_risk_class": "Not applicable",
    "scheme_objective": "The investment strategy seeks to generate alpha over the long term by investing across a spectrum of large, mid and small cap companies using long/short equity strategies. \nThere is no assurance that the investment objective of the investment strategy will be achieved.",
    "face_value": "1000",
    "nfo_open_date": "2026-04-10",
    "nfo_close_date": "2026-04-24",
    "allotment_date": "2026-04-29",
    "reopen_date": "2026-05-04",
    "maturity_date": "Not applicable",
    "benchmark_tier_1": "Nifty 500 TRI",
    "benchmark_tier_2": "Not applicable",
    "asset_allocation": [
        {
            "allocation_type": "",
            "minimum_percentage": 80,
            "maximum_percentage": 100
        },
        {
            "allocation_type": "",
            "minimum_percentage": 0,
            "maximum_percentage": 25
        },
        {
            "allocation_type": "",
            "minimum_percentage": 0,
            "maximum_percentage": 20
        }
    ],
    "listing_details": "Not listed",
    "plans": {
        "regular": {
            "growth": {
                "name": "SIF-96",
                "amfi_code": "SIF-96",
                "isin_code": "INF090I30030",
                "rta_code": "INR000002813",
                "additional_plans": [
                    {
                        "name": "INF090I30055",
                        "isin_code": "INF090I30055",
                        "rta_code": "INR000002813"
                    },
                    {
                        "name": "INF090I30063",
                        "isin_code": "INF090I30063",
                        "rta_code": "INR000002813"
                    }
                ]
            },
            "idcw": {
                "payout": {},
                "reinvestment": {
                    "name": "Regular – Growth Income Distribution cum capital withdrawal (IDCW) Plan (Payout and Reinvestment options)",
                    "amfi_code": "SIF-95",
                    "isin_code": "INF090I30014",
                    "rta_code": "INR000002813"
                },
                "transfer": {},
                "time_period": {},
                "unknown": {}
            }
        },
        "direct": {
            "growth": {
                "name": "SIF-97",
                "amfi_code": "SIF-97",
                "isin_code": "INF090I30048",
                "rta_code": "INR000002813"
            },
            "idcw": {
                "payout": {},
                "reinvestment": {
                    "name": "Direct – Growth Income Distribution cum capital withdrawal (IDCW) Plan (Payout and Reinvestment options)",
                    "amfi_code": "SIF-94",
                    "isin_code": "INF090I30022",
                    "rta_code": "INR000002813"
                },
                "transfer": {},
                "time_period": {},
                "unknown": {}
            }
        }
    },
    "fund_managers": [
        {
            "name": "Arihant Jain",
            "type": "Primary",
            "from": "Arihant Jain: April 29, 2026",
            "to": null,
            "role_or_portion": null
        }
    ],
    "investment_limits": {
        "minimum_application_amount": "1000000",
        "application_multiple": "10000",
        "minimum_additional_amount": "10000",
        "additional_multiple": "1000",
        "minimum_redemption_amount": "10000",
        "minimum_redemption_units": "Not applicable"
    },
    "exit_load": "1% if units are redeemed within one year of allotment, NIL thereafter.",
    "registrar": "CAMS",
    "custodian": "Hongkong and Shanghai Banking Corporation Limited (HSBC)",
    "auditor": "B S R & Co. LLP",
    "sif_name": "Franklin Templeton Mutual Fund"
}